{"title":"Jitter Operators","description":"List of Gen operators exclusive to Jitter Gen","headings":[{"depth":1,"id":"jitter-operators","text":"Jitter Operators"},{"depth":2,"id":"color","text":"Color"},{"depth":2,"id":"coordinate","text":"Coordinate"},{"depth":2,"id":"quaternion","text":"Quaternion"},{"depth":2,"id":"sampling","text":"Sampling"},{"depth":2,"id":"surface","text":"Surface"},{"depth":2,"id":"vector","text":"Vector"}],"patchers":[],"content":"\"use strict\";\nconst {Fragment: _Fragment, jsx: _jsx, jsxs: _jsxs} = arguments[0];\nfunction _createMdxContent(props) {\n  const _components = {\n    a: \"a\",\n    annotation: \"annotation\",\n    h1: \"h1\",\n    h2: \"h2\",\n    li: \"li\",\n    math: \"math\",\n    mi: \"mi\",\n    mn: \"mn\",\n    mo: \"mo\",\n    mrow: \"mrow\",\n    msup: \"msup\",\n    p: \"p\",\n    semantics: \"semantics\",\n    span: \"span\",\n    ul: \"ul\",\n    ...props.components\n  };\n  return _jsxs(_Fragment, {\n    children: [_jsx(_components.h1, {\n      id: \"jitter-operators\",\n      children: \"Jitter Operators\"\n    }), \"\\n\", _jsxs(_components.p, {\n      children: [\"The following Gen operators are unique to the \", _jsx(_components.a, {\n        href: \"/reference/jit.gen\",\n        title: \"jit.gen\",\n        children: \"jit.gen\"\n      }), \", \", _jsx(_components.a, {\n        href: \"/reference/jit.pix\",\n        title: \"jit.pix\",\n        children: \"jit.pix\"\n      }), \", and \", _jsx(_components.a, {\n        href: \"/reference/jit.gl.pix\",\n        title: \"jit.gl.pix\",\n        children: \"jit.gl.pix\"\n      }), \" objects - unlike the Common Gen Operators , they are only used in the matrix/texture domain.\"]\n    }), \"\\n\", _jsx(_components.h2, {\n      id: \"color\",\n      children: \"Color\"\n    }), \"\\n\", _jsxs(_components.ul, {\n      children: [\"\\n\", _jsxs(_components.li, {\n        children: [\"\\n\", _jsxs(_components.p, {\n          children: [_jsx(_components.a, {\n            href: \"/reference/gen_jit_hsl2rgb\",\n            className: \"c74-object-link\",\n            children: \"hsl2rgb\"\n          }), \" : Convert HSL to RGB, preserving alpha\"]\n        }), \"\\n\"]\n      }), \"\\n\", _jsxs(_components.li, {\n        children: [\"\\n\", _jsxs(_components.p, {\n          children: [_jsx(_components.a, {\n            href: \"/reference/gen_jit_rgb2hsl\",\n            className: \"c74-object-link\",\n            children: \"rgb2hsl\"\n          }), \" : Convert RGB to HSL, preserving alpha\"]\n        }), \"\\n\"]\n      }), \"\\n\"]\n    }), \"\\n\", _jsx(_components.h2, {\n      id: \"coordinate\",\n      children: \"Coordinate\"\n    }), \"\\n\", _jsxs(_components.ul, {\n      children: [\"\\n\", _jsxs(_components.li, {\n        children: [\"\\n\", _jsxs(_components.p, {\n          children: [_jsx(_components.a, {\n            href: \"/reference/gen_jit_cell\",\n            className: \"c74-object-link\",\n            children: \"cell\"\n          }), \" : Cell coordinates of input matrix [0, dim-1]\"]\n        }), \"\\n\"]\n      }), \"\\n\", _jsxs(_components.li, {\n        children: [\"\\n\", _jsxs(_components.p, {\n          children: [_jsx(_components.a, {\n            href: \"/reference/gen_jit_dim\",\n            className: \"c74-object-link\",\n            children: \"dim\"\n          }), \" : Dimensions of input matrix\"]\n        }), \"\\n\"]\n      }), \"\\n\", _jsxs(_components.li, {\n        children: [\"\\n\", _jsxs(_components.p, {\n          children: [_jsx(_components.a, {\n            href: \"/reference/gen_jit_norm\",\n            className: \"c74-object-link\",\n            children: \"norm\"\n          }), \" : Normalized coordinates of input matrix [0, 1]\"]\n        }), \"\\n\"]\n      }), \"\\n\", _jsxs(_components.li, {\n        children: [\"\\n\", _jsxs(_components.p, {\n          children: [_jsx(_components.a, {\n            href: \"/reference/gen_jit_snorm\",\n            className: \"c74-object-link\",\n            children: \"snorm\"\n          }), \" : Signed normalized coordinates of input matrix [-1, 1]\"]\n        }), \"\\n\"]\n      }), \"\\n\"]\n    }), \"\\n\", _jsx(_components.h2, {\n      id: \"quaternion\",\n      children: \"Quaternion\"\n    }), \"\\n\", _jsxs(_components.ul, {\n      children: [\"\\n\", _jsxs(_components.li, {\n        children: [\"\\n\", _jsxs(_components.p, {\n          children: [_jsx(_components.a, {\n            href: \"/reference/gen_jit_qconj\",\n            className: \"c74-object-link\",\n            children: \"qconj\"\n          }), \" : Get the conjugate of a quaternion.\"]\n        }), \"\\n\"]\n      }), \"\\n\", _jsxs(_components.li, {\n        children: [\"\\n\", _jsxs(_components.p, {\n          children: [_jsx(_components.a, {\n            href: \"/reference/gen_jit_qmul\",\n            className: \"c74-object-link\",\n            children: \"qmul\"\n          }), \" : Multiply quaternion inputs\"]\n        }), \"\\n\"]\n      }), \"\\n\", _jsxs(_components.li, {\n        children: [\"\\n\", _jsxs(_components.p, {\n          children: [_jsx(_components.a, {\n            href: \"/reference/gen_jit_qrot\",\n            className: \"c74-object-link\",\n            children: \"qrot\"\n          }), \" : Rotate a vector by a quaternion. The equation of the rotation is \", _jsxs(_components.span, {\n            className: \"katex\",\n            children: [_jsx(_components.span, {\n              className: \"katex-mathml\",\n              children: _jsx(_components.math, {\n                xmlns: \"http://www.w3.org/1998/Math/MathML\",\n                children: _jsxs(_components.semantics, {\n                  children: [_jsxs(_components.mrow, {\n                    children: [_jsx(_components.mi, {\n                      children: \"q\"\n                    }), _jsx(_components.mo, {\n                      children: \"∗\"\n                    }), _jsx(_components.mi, {\n                      children: \"v\"\n                    }), _jsx(_components.mo, {\n                      children: \"∗\"\n                    }), _jsxs(_components.msup, {\n                      children: [_jsx(_components.mi, {\n                        children: \"q\"\n                      }), _jsxs(_components.mrow, {\n                        children: [_jsx(_components.mo, {\n                          children: \"−\"\n                        }), _jsx(_components.mn, {\n                          children: \"1\"\n                        })]\n                      })]\n                    })]\n                  }), _jsx(_components.annotation, {\n                    encoding: \"application/x-tex\",\n                    children: \"q*v*q^{-1}\"\n                  })]\n                })\n              })\n            }), _jsxs(_components.span, {\n              className: \"katex-html\",\n              \"aria-hidden\": \"true\",\n              children: [_jsxs(_components.span, {\n                className: \"base\",\n                children: [_jsx(_components.span, {\n                  className: \"strut\",\n                  style: {\n                    height: \"0.6597em\",\n                    verticalAlign: \"-0.1944em\"\n                  }\n                }), _jsx(_components.span, {\n                  className: \"mord mathnormal\",\n                  style: {\n                    marginRight: \"0.03588em\"\n                  },\n                  children: \"q\"\n                }), _jsx(_components.span, {\n                  className: \"mspace\",\n                  style: {\n                    marginRight: \"0.2222em\"\n                  }\n                }), _jsx(_components.span, {\n                  className: \"mbin\",\n                  children: \"∗\"\n                }), _jsx(_components.span, {\n                  className: \"mspace\",\n                  style: {\n                    marginRight: \"0.2222em\"\n                  }\n                })]\n              }), _jsxs(_components.span, {\n                className: \"base\",\n                children: [_jsx(_components.span, {\n                  className: \"strut\",\n                  style: {\n                    height: \"0.4653em\"\n                  }\n                }), _jsx(_components.span, {\n                  className: \"mord mathnormal\",\n                  style: {\n                    marginRight: \"0.03588em\"\n                  },\n                  children: \"v\"\n                }), _jsx(_components.span, {\n                  className: \"mspace\",\n                  style: {\n                    marginRight: \"0.2222em\"\n                  }\n                }), _jsx(_components.span, {\n                  className: \"mbin\",\n                  children: \"∗\"\n                }), _jsx(_components.span, {\n                  className: \"mspace\",\n                  style: {\n                    marginRight: \"0.2222em\"\n                  }\n                })]\n              }), _jsxs(_components.span, {\n                className: \"base\",\n                children: [_jsx(_components.span, {\n                  className: \"strut\",\n                  style: {\n                    height: \"1.0085em\",\n                    verticalAlign: \"-0.1944em\"\n                  }\n                }), _jsxs(_components.span, {\n                  className: \"mord\",\n                  children: [_jsx(_components.span, {\n                    className: \"mord mathnormal\",\n                    style: {\n                      marginRight: \"0.03588em\"\n                    },\n                    children: \"q\"\n                  }), _jsx(_components.span, {\n                    className: \"msupsub\",\n                    children: _jsx(_components.span, {\n                      className: \"vlist-t\",\n                      children: _jsx(_components.span, {\n                        className: \"vlist-r\",\n                        children: _jsx(_components.span, {\n                          className: \"vlist\",\n                          style: {\n                            height: \"0.8141em\"\n                          },\n                          children: _jsxs(_components.span, {\n                            style: {\n                              top: \"-3.063em\",\n                              marginRight: \"0.05em\"\n                            },\n                            children: [_jsx(_components.span, {\n                              className: \"pstrut\",\n                              style: {\n                                height: \"2.7em\"\n                              }\n                            }), _jsx(_components.span, {\n                              className: \"sizing reset-size6 size3 mtight\",\n                              children: _jsxs(_components.span, {\n                                className: \"mord mtight\",\n                                children: [_jsx(_components.span, {\n                                  className: \"mord mtight\",\n                                  children: \"−\"\n                                }), _jsx(_components.span, {\n                                  className: \"mord mtight\",\n                                  children: \"1\"\n                                })]\n                              })\n                            })]\n                          })\n                        })\n                      })\n                    })\n                  })]\n                })]\n              })]\n            })]\n          }), \".\"]\n        }), \"\\n\"]\n      }), \"\\n\"]\n    }), \"\\n\", _jsx(_components.h2, {\n      id: \"sampling\",\n      children: \"Sampling\"\n    }), \"\\n\", _jsxs(_components.ul, {\n      children: [\"\\n\", _jsxs(_components.li, {\n        children: [\"\\n\", _jsxs(_components.p, {\n          children: [_jsx(_components.a, {\n            href: \"/reference/gen_jit_nearest\",\n            className: \"c74-object-link\",\n            children: \"nearest\"\n          }), \" : Nearest neighbor sample a matrix at a given coordinate (normalized). Nearest has a boundmode attribute that can be set to wrap, mirror or clamp.\"]\n        }), \"\\n\"]\n      }), \"\\n\", _jsxs(_components.li, {\n        children: [\"\\n\", _jsxs(_components.p, {\n          children: [_jsx(_components.a, {\n            href: \"/reference/gen_jit_nearestpix\",\n            className: \"c74-object-link\",\n            children: \"nearestpix\"\n          }), \" : Nearest neighbor sample a matrix at a given coordinate (in pixels). Nearest has a boundmode attribute that can be set to wrap, mirror or clamp.\"]\n        }), \"\\n\"]\n      }), \"\\n\", _jsxs(_components.li, {\n        children: [\"\\n\", _jsxs(_components.p, {\n          children: [_jsx(_components.a, {\n            href: \"/reference/gen_jit_sample\",\n            className: \"c74-object-link\",\n            children: \"sample\"\n          }), \" : Sample a matrix at a given coordinate (normalized) with linear interpolation. Sample has a boundmode attribute that can be set to wrap, mirror or clamp.\"]\n        }), \"\\n\"]\n      }), \"\\n\", _jsxs(_components.li, {\n        children: [\"\\n\", _jsxs(_components.p, {\n          children: [_jsx(_components.a, {\n            href: \"/reference/gen_jit_samplepix\",\n            className: \"c74-object-link\",\n            children: \"samplepix\"\n          }), \" : Sample a matrix at a given coordinate (in pixels) with linear interpolation. Pixel centers are located at PIXEL+0.5. For example, the center of the upper-left pixel is (0.5, 0.5). Samplepix has a boundmode attribute that can be set to wrap, mirror or clamp.\"]\n        }), \"\\n\"]\n      }), \"\\n\"]\n    }), \"\\n\", _jsx(_components.h2, {\n      id: \"surface\",\n      children: \"Surface\"\n    }), \"\\n\", _jsxs(_components.ul, {\n      children: [\"\\n\", _jsxs(_components.li, {\n        children: [\"\\n\", _jsxs(_components.p, {\n          children: [_jsx(_components.a, {\n            href: \"/reference/gen_jit_circle\",\n            className: \"c74-object-link\",\n            children: \"circle\"\n          }), \" : Equation of a circle taking input coordinates ranging from [0, 1]\"]\n        }), \"\\n\"]\n      }), \"\\n\", _jsxs(_components.li, {\n        children: [\"\\n\", _jsxs(_components.p, {\n          children: [_jsx(_components.a, {\n            href: \"/reference/gen_jit_cone\",\n            className: \"c74-object-link\",\n            children: \"cone\"\n          }), \" : Equation of a cone taking input coordinates ranging from [0, 1]\"]\n        }), \"\\n\"]\n      }), \"\\n\", _jsxs(_components.li, {\n        children: [\"\\n\", _jsxs(_components.p, {\n          children: [_jsx(_components.a, {\n            href: \"/reference/gen_jit_cylinder\",\n            className: \"c74-object-link\",\n            children: \"cylinder\"\n          }), \" : Equation of a cylinder taking input coordinates ranging from [0, 1]\"]\n        }), \"\\n\"]\n      }), \"\\n\", _jsxs(_components.li, {\n        children: [\"\\n\", _jsxs(_components.p, {\n          children: [_jsx(_components.a, {\n            href: \"/reference/gen_jit_plane\",\n            className: \"c74-object-link\",\n            children: \"plane\"\n          }), \" : Equation of a plane taking input coordinates ranging from [0, 1]\"]\n        }), \"\\n\"]\n      }), \"\\n\", _jsxs(_components.li, {\n        children: [\"\\n\", _jsxs(_components.p, {\n          children: [_jsx(_components.a, {\n            href: \"/reference/gen_jit_sphere\",\n            className: \"c74-object-link\",\n            children: \"sphere\"\n          }), \" : Equation of a sphere taking input coordinates ranging from [0, 1]\"]\n        }), \"\\n\"]\n      }), \"\\n\", _jsxs(_components.li, {\n        children: [\"\\n\", _jsxs(_components.p, {\n          children: [_jsx(_components.a, {\n            href: \"/reference/gen_jit_torus\",\n            className: \"c74-object-link\",\n            children: \"torus\"\n          }), \" : Equation of a torus taking input coordinates ranging from [0, 1]\"]\n        }), \"\\n\"]\n      }), \"\\n\"]\n    }), \"\\n\", _jsx(_components.h2, {\n      id: \"vector\",\n      children: \"Vector\"\n    }), \"\\n\", _jsxs(_components.ul, {\n      children: [\"\\n\", _jsxs(_components.li, {\n        children: [\"\\n\", _jsxs(_components.p, {\n          children: [_jsx(_components.a, {\n            href: \"/reference/gen_jit_concat\",\n            className: \"c74-object-link\",\n            children: \"concat\"\n          }), \" : Concatenate vector values into a larger vector\"]\n        }), \"\\n\"]\n      }), \"\\n\", _jsxs(_components.li, {\n        children: [\"\\n\", _jsxs(_components.p, {\n          children: [_jsx(_components.a, {\n            href: \"/reference/gen_jit_cross\",\n            className: \"c74-object-link\",\n            children: \"cross\"\n          }), \" : Take the cross product of two vectors\"]\n        }), \"\\n\"]\n      }), \"\\n\", _jsxs(_components.li, {\n        children: [\"\\n\", _jsxs(_components.p, {\n          children: [_jsx(_components.a, {\n            href: \"/reference/gen_jit_dot\",\n            className: \"c74-object-link\",\n            children: \"dot\"\n          }), \" : Take the dot product of two vectors\"]\n        }), \"\\n\"]\n      }), \"\\n\", _jsxs(_components.li, {\n        children: [\"\\n\", _jsxs(_components.p, {\n          children: [_jsx(_components.a, {\n            href: \"/reference/gen_jit_faceforward\",\n            className: \"c74-object-link\",\n            children: \"faceforward\"\n          }), \" : Return a vector pointing in the same direction as another\"]\n        }), \"\\n\"]\n      }), \"\\n\", _jsxs(_components.li, {\n        children: [\"\\n\", _jsxs(_components.p, {\n          children: [_jsx(_components.a, {\n            href: \"/reference/gen_jit_length\",\n            className: \"c74-object-link\",\n            children: \"length\"\n          }), \" : Returns the length of a vector\"]\n        }), \"\\n\"]\n      }), \"\\n\", _jsxs(_components.li, {\n        children: [\"\\n\", _jsxs(_components.p, {\n          children: [_jsx(_components.a, {\n            href: \"/reference/gen_jit_normalize\",\n            className: \"c74-object-link\",\n            children: \"normalize\"\n          }), \" : Normalize a vector to unit length\"]\n        }), \"\\n\"]\n      }), \"\\n\", _jsxs(_components.li, {\n        children: [\"\\n\", _jsxs(_components.p, {\n          children: [_jsx(_components.a, {\n            href: \"/reference/gen_jit_reflect\",\n            className: \"c74-object-link\",\n            children: \"reflect\"\n          }), \" : Reflect a vector off a surface defined by a normal\"]\n        }), \"\\n\"]\n      }), \"\\n\", _jsxs(_components.li, {\n        children: [\"\\n\", _jsxs(_components.p, {\n          children: [_jsx(_components.a, {\n            href: \"/reference/gen_jit_refract\",\n            className: \"c74-object-link\",\n            children: \"refract\"\n          }), \" : Refract a vector through a surface defined by a normal and a refraction index\"]\n        }), \"\\n\"]\n      }), \"\\n\", _jsxs(_components.li, {\n        children: [\"\\n\", _jsxs(_components.p, {\n          children: [_jsx(_components.a, {\n            href: \"/reference/gen_jit_rotor\",\n            className: \"c74-object-link\",\n            children: \"rotor\"\n          }), \" : Return a quaternion that can rotate the first input into the second.\"]\n        }), \"\\n\"]\n      }), \"\\n\", _jsxs(_components.li, {\n        children: [\"\\n\", _jsxs(_components.p, {\n          children: [_jsx(_components.a, {\n            href: \"/reference/gen_jit_swiz\",\n            className: \"c74-object-link\",\n            children: \"swiz\"\n          }), \" : Unpack and remap vector components\"]\n        }), \"\\n\"]\n      }), \"\\n\", _jsxs(_components.li, {\n        children: [\"\\n\", _jsxs(_components.p, {\n          children: [_jsx(_components.a, {\n            href: \"/reference/gen_jit_vec\",\n            className: \"c74-object-link\",\n            children: \"vec\"\n          }), \" : Pack scalar values into a vector\"]\n        }), \"\\n\"]\n      }), \"\\n\"]\n    })]\n  });\n}\nfunction MDXContent(props = {}) {\n  const {wrapper: MDXLayout} = props.components || ({});\n  return MDXLayout ? _jsx(MDXLayout, {\n    ...props,\n    children: _jsx(_createMdxContent, {\n      ...props\n    })\n  }) : _createMdxContent(props);\n}\nreturn {\n  default: MDXContent\n};\n","tags":[],"kind":"","contributors":[],"publishDate":"2024-10-30T12:00:00.000Z","categories":[],"files":[],"articles":[]}